pymepack/__init__.py
pymepack/pymepack_def.pxd
pymepack/pymepack_impl.cpython-38-x86_64-linux-gnu.so
pymepack/generator/__init__.py
pymepack/generator/benchmarks.cpython-38-x86_64-linux-gnu.so
pymepack/lapack/__init__.py
pymepack/lapack/lapack.cpython-38-x86_64-linux-gnu.so
pymepack/tests/__init__.py
pymepack/tests/tests.py
pymepack.libs/libgfortran-040039e1.so.5.0.0
pymepack.libs/libgomp-a34b3233.so.1.0.0
pymepack.libs/libmepack-1c5aa3c9.so.1.1.2
pymepack.libs/libopenblasp-r0-945a50b9.3.30.so
pymepack.libs/libquadmath-96973f99.so.0.0.0
pymepack-1.1.2.dist-info/LICENSE
pymepack-1.1.2.dist-info/METADATA
pymepack-1.1.2.dist-info/WHEEL
pymepack-1.1.2.dist-info/top_level.txt
pymepack-1.1.2.dist-info/RECORD
pymepack-1.1.2.dist-info/sboms/auditwheel.cdx.json
