Metadata-Version: 2.1
Name: pymepack
Version: 1.1.2
Summary: A wrapper for the MEPACK (Matrix Equation Package) library
Author-email: Martin Koehler <koehlerm@mpi-magdeburg.mpg.de>, Aleksey Maleyko <maleyko@mpi-magdeburg.mpg.de>
Maintainer-email: Martin Koehler <koehlerm@mpi-magdeburg.mpg.de>
Project-URL: homepage, https://gitlab.mpi-magdeburg.mpg.de/software/pymepack
Classifier: Development Status :: 5 - Production/Stable
Classifier: Intended Audience :: Science/Research
Classifier: Intended Audience :: Developers
Classifier: License :: OSI Approved :: GNU General Public License v3 or later (GPLv3+)
Classifier: Operating System :: OS Independent
Classifier: Programming Language :: Cython
Classifier: Programming Language :: Python
Classifier: Programming Language :: Python :: 3.7
Classifier: Programming Language :: Python :: 3.8
Classifier: Programming Language :: Python :: 3.9
Classifier: Programming Language :: Python :: 3.10
Classifier: Programming Language :: Python :: 3.11
Classifier: Programming Language :: Python :: 3.12
Classifier: Topic :: Software Development
Classifier: Topic :: Scientific/Engineering
Classifier: Topic :: Scientific/Engineering :: Mathematics
Requires-Python: >=3.8.0
License-File: LICENSE
Requires-Dist: scipy>=1.5.4
Requires-Dist: parameterized>=0.8.0
Requires-Dist: numpy<2,>=1.21.3; python_version >= "3.10" and python_version < "3.11"
Requires-Dist: numpy<2,>=1.23.2; python_version >= "3.11" and python_version < "3.12"
Requires-Dist: numpy>=1.26.0; python_version >= "3.12" and python_version < "3.13"
Requires-Dist: numpy>=1.26.2; python_version >= "3.13"
Requires-Dist: numpy<2,>=1.20.3; python_version >= "3.7" and python_version < "3.10"
